gsheetgraph/__init__.py
gsheetgraph/creds.json
gsheetgraph/gsheet_api.py
gsheetgraph-0.1.3.dist-info/METADATA
gsheetgraph-0.1.3.dist-info/RECORD
gsheetgraph-0.1.3.dist-info/WHEEL
gsheetgraph-0.1.3.dist-info/top_level.txt
