Metadata-Version: 2.1
Name: gsheetgraph
Version: 0.1.3
Summary: this is gsheetgraph package
Home-page: UNKNOWN
Author: Neeraj Kumar
Author-email: neeraj.neerajkumar11@gmail.com
License: MIT
Platform: UNKNOWN
Classifier: License :: OSI Approved :: MIT License
Classifier: Programming Language :: Python :: 3.6
Classifier: Programming Language :: Python :: 3.7
Classifier: Programming Language :: Python :: 3.8
